gr_tradinggame/__init__.py
gr_tradinggame/py.typed
gr_tradinggame/coding/__init__.py
gr_tradinggame/coding/blackbox.py
gr_tradinggame/coding/client.py
gr_tradinggame/coding/gui.py
gr_tradinggame/coding/server.py
gr_tradinggame/coding/util.py
gr_tradinggame/manual/__init__.py
gr_tradinggame-0.1.12.dist-info/METADATA
gr_tradinggame-0.1.12.dist-info/WHEEL
gr_tradinggame-0.1.12.dist-info/RECORD
